unitools/ICMPv4.py
unitools/TCPv4.py
unitools/__init__.py
unitools/tests/__init__.py
unitools/utils/IPHelpers.py
unitools/utils/__init__.py
unitools-0.1.2.dist-info/LICENSE
unitools-0.1.2.dist-info/METADATA
unitools-0.1.2.dist-info/WHEEL
unitools-0.1.2.dist-info/top_level.txt
unitools-0.1.2.dist-info/RECORD
