Metadata-Version: 2.1
Name: unitools
Version: 0.1.2
Summary: A python library that contains various tools that I have found useful over the years.
Home-page: https://github.com/MrTwister96/unitools
Author: Schalk Olivier
Author-email: olivierschalk1@gmail.com
License: MIT
Classifier: Development Status :: 3 - Alpha
Classifier: Intended Audience :: Developers
Classifier: License :: OSI Approved :: MIT License
Classifier: Programming Language :: Python :: 3
Classifier: Programming Language :: Python :: 3.6
Classifier: Programming Language :: Python :: 3.7
Classifier: Programming Language :: Python :: 3.8
Classifier: Programming Language :: Python :: 3.9
Classifier: Programming Language :: Python :: 3.10
Requires-Python: >=3.6
License-File: LICENSE
